zoinks/__init__.py
zoinks/analyzer.py
zoinks/macros.py
zoinks/main.py
tsa_zoinks-0.1.2.dist-info/LICENSE
tsa_zoinks-0.1.2.dist-info/METADATA
tsa_zoinks-0.1.2.dist-info/WHEEL
tsa_zoinks-0.1.2.dist-info/entry_points.txt
tsa_zoinks-0.1.2.dist-info/top_level.txt
tsa_zoinks-0.1.2.dist-info/RECORD
