Metadata-Version: 2.1
Name: tsa-zoinks
Version: 0.1.2
Home-page: https://gitflic.ru/project/a2sh3r/zoinks
Author: Zainutdinov Mikhail
Author-email: michaelzainutdinov@ya.ru
Classifier: Programming Language :: Python :: 3
Classifier: License :: OSI Approved :: MIT License
License-File: LICENSE
Requires-Dist: colorama
